jsonclass/__init__.py
jsonclass/dumps.py
jsonclass/jsonclass.py
jsonclass/loads.py
jsonclass-0.0.9.dist-info/METADATA
jsonclass-0.0.9.dist-info/WHEEL
jsonclass-0.0.9.dist-info/licenses/LICENSE
jsonclass-0.0.9.dist-info/RECORD
